PWE_Diagnostic_Lattice_Tool/ASPConstraintMap.py
PWE_Diagnostic_Lattice_Tool/ASP_LogicProgram.py
PWE_Diagnostic_Lattice_Tool/BitConstraintMap.py
PWE_Diagnostic_Lattice_Tool/ConstraintMap.py
PWE_Diagnostic_Lattice_Tool/DiagnosisAlgorithms.py
PWE_Diagnostic_Lattice_Tool/LatticeNode.py
PWE_Diagnostic_Lattice_Tool/LogicProgram.py
PWE_Diagnostic_Lattice_Tool/PowersetBitLib.py
PWE_Diagnostic_Lattice_Tool/PowersetFullLatticeViz.py
PWE_Diagnostic_Lattice_Tool/PowersetSummaryLatticeViz.py
PWE_Diagnostic_Lattice_Tool/__init__.py
PWE_Diagnostic_Lattice_Tool-0.0.2.dist-info/LICENSE
PWE_Diagnostic_Lattice_Tool-0.0.2.dist-info/METADATA
PWE_Diagnostic_Lattice_Tool-0.0.2.dist-info/WHEEL
PWE_Diagnostic_Lattice_Tool-0.0.2.dist-info/top_level.txt
PWE_Diagnostic_Lattice_Tool-0.0.2.dist-info/RECORD
