Metadata-Version: 2.1
Name: PWE-Diagnostic-Lattice-Tool
Version: 0.0.2
Summary: Companion Tool to PWE for problems with switchable constraints.
Home-page: https://github.com/idaks/PWE-Diagnostic-Lattice-Tool
Author: Sahil Gupta
Author-email: 
License: UNKNOWN
Platform: UNKNOWN
Classifier: Programming Language :: Python :: 3
Classifier: License :: OSI Approved :: Apache Software License
Classifier: Operating System :: OS Independent
Requires-Dist: pw-explorer (>=0.0.23)
Requires-Dist: networkx (>=2.2)
Requires-Dist: nxpd (>=0.2.0)
Requires-Dist: pandas (>=0.24.1)
Requires-Dist: numpy (>=1.16.2)
